sysdep/__init__.py
sysdep/cli.py
sysdep/config.py
sysdep/setuptools_integration.py
sysdep/utils.py
sysdep/checkers/base.py
sysdep/checkers/executable.py
sysdep/checkers/library.py
sysdep/generators/requirements_generator.py
sysdep/mappers/__init__.py
sysdep/mappers/core.py
sysdep/mappers/dependency_data.py
sysdep/mappers/name_normalizer.py
sysdep/parsers/code_scanner.py
sysdep/parsers/manifest.py
sysdep/parsers/python_deps.py
sysdep/platforms/__init__.py
sysdep/platforms/base.py
sysdep/platforms/linux.py
sysdep/platforms/macos.py
sysdep/platforms/windows.py
sysdep-0.1.4.dist-info/LICENSE
sysdep-0.1.4.dist-info/METADATA
sysdep-0.1.4.dist-info/WHEEL
sysdep-0.1.4.dist-info/entry_points.txt
sysdep-0.1.4.dist-info/top_level.txt
sysdep-0.1.4.dist-info/RECORD
