Metadata-Version: 2.2
Name: sysdep
Version: 0.1.4
Summary: System Dependency Checker for Python Projects
Author: Latiful Mousom
Author-email: Latiful Mousom <latifulmousom@gmail.com>
License: MIT
Project-URL: Homepage, https://github.com/lmousom/sysdep
Project-URL: Issues, https://github.com/lmousom/sysdep/issues
Keywords: dependency,system,package,verification,installation
Classifier: Development Status :: 4 - Beta
Classifier: Intended Audience :: Developers
Classifier: License :: OSI Approved :: MIT License
Classifier: Programming Language :: Python :: 3
Classifier: Programming Language :: Python :: 3.7
Classifier: Programming Language :: Python :: 3.8
Classifier: Programming Language :: Python :: 3.9
Classifier: Programming Language :: Python :: 3.10
Classifier: Programming Language :: Python :: 3.11
Classifier: Topic :: Software Development :: Libraries :: Python Modules
Requires-Python: >=3.7
License-File: LICENSE
Provides-Extra: dev
Requires-Dist: pytest>=6.0.0; extra == "dev"
Requires-Dist: black>=21.5b2; extra == "dev"
Requires-Dist: isort>=5.0.0; extra == "dev"
Requires-Dist: mypy>=0.800; extra == "dev"
Requires-Dist: ui; extra == "dev"
Provides-Extra: ui
Requires-Dist: tqdm>=4.46.0; extra == "ui"
Dynamic: author
Dynamic: requires-python
